{
  "id": "cova-de-na-barxa",
  "name": "Cova de Na Barxa, de sa Bassa, o de n'Aladern",
  "name_english": "Na Barxa Cave (also: Sa Bassa Cave / N'Aladern Cave)",
  "municipality": "Capdepera",
  "url": "http://www.mallorcaverde.es/cova-de-na-barxa.htm",
  "starting_point": "Font de sa Cala. Walk from the beach, coast toward Cala Ratjada, passing Caló de n'Aladern to Punta na Baixa where the cave is located.",
  "footwear": "Mountain boots",
  "clothing": "Shorts or a wetsuit for entering the lake",
  "elevation_change": "None",
  "distance": "Approximately 670 m",
  "aesthetics": 3,
  "aesthetics_max": 5,
  "magnitude": "III",
  "magnitude_value": 3,
  "difficulty": "III",
  "difficulty_value": 3,
  "altitude": "4 m",
  "origin": "Karstic",
  "route_type": "Predominantly horizontal",
  "depth": "-4 m",
  "approach_time": "Approximately 10 minutes",
  "best_season": "Swimming season, to also enjoy a swim",
  "access": "Own vehicle",
  "coordinates_utm": "539316 E, 4392973 N (DATUM EUROPEAN 1950) / 539225 E, 4392775 N (DATUM WGS84)",
  "equipment": "Helmet, lighting, an 8-9 m rope, and water boots",
  "last_updated": "8 de Julio del 2007",
  "description": "A coastal cave featuring a marine-influenced underground lake that must be waded or swum through to explore further chambers. The decorated interior includes a beautiful gour, a 4-meter column, and flowstones. The cave is home to a bat colony and has yielded prehistoric aquatic fauna, including numerous new crustacean species. Designated a site of special biological interest.",
  "full_description": "With the description of the Cova de Na Barxa, we come into contact with water for the first time. What I mean is that until now many of the cavities covered by Mallorca Verde contained lakes inside them — in some cases, and as I recall at this moment, up to five as is the case with the Cova des Pont — but I had never described any cavity in which we had to wade into any of them, either to cross them or to continue the visit of the cave from the water. This is the first time we do so, and for this we have chosen one in which, if we enter in summer, it is not even necessary to wear a wetsuit.\n\nOnce we find ourselves at the entrance of the cavity, of considerable dimensions — 2.5 meters high and a little more than 1 meter wide — upon looking inside we can see that to go in we have to descend by downclimbing about 3 meters, holding onto the rock which is quite slippery (at least that is how it was the day I accessed it), so it is advisable to bring a rope in case it is needed.\n\nOnce inside, it is possible that the seawater covers the gallery a little more than a hand's width in its entirety, or that the water from the marine incursion only reaches the height of the entrance through which we have accessed. In any case, it is better to wear appropriate footwear for the water, such as simple rubber boots or mountain boots that may already be a little old. Once on dry land, we can observe how the water depth increases in the direction of the sea, although the light that could come from the outside is not visible, while if we head in the opposite direction it decreases. To continue visiting the cavity, we have to begin climbing without any danger while ducking since the passage is low in height, to access the chamber, which we can do from two different spots that are next to each other. If we do it through the one next to the right wall in the direction of travel, this one is a bit lower and at the same time a bit narrow, so perhaps — and especially if one is not very slim — the most advisable thing is to climb a little higher and then descend to the entry point of the aforementioned passage, and from that place wade into the water of the lake that is on this side of the chamber and that prevents us from continuing forward unless it is through it.\n\nOnce in the water, one must head toward the left side in the direction of travel, so we will have to hold onto the rocks with our hands in order to access a place where the depth of the lake is less, although it is not stable and can change from one time to another. By shining the light on the lake water, we can observe, thanks to its crystalline clarity, the path to follow to cross to the other side and continue the visit.\n\nOnce at the other end of the lake, we must ascend a small ramp to the highest part of the cave, which is a kind of 'plateau' from where one can have a perspective of the entire cave except for the entrance gallery. If we head to the right, going down a little, we will reach the most decorated part of the cave, where a beautiful gour stands out next to a flowstone that is undoubtedly the one that supplies it with water. Also noteworthy near the gour is an interesting column of a little more than four meters, and just behind the flowstone there is a kind of ledge that allows us to contemplate the lake and the chamber we are in from another perspective.\n\nThe dimensions of this chamber are approximately forty meters wide by the same length, where we include the beautiful lake that so embellishes this cavity. The ceiling height at the highest part I do not believe exceeds more than ten meters.\n\nThis cave serves as a refuge for a community of bats, so great care must be taken not to disturb them. A certain amount of guano (natural fertilizer created from the droppings of certain types of birds and bats) can be found in various places. Guano has been used as organic fertilizer on many occasions throughout history due to its properties.\n\nIn the lake of this cave, as well as in that of others in this coastal area — such as the Drac cave in Porto Cristo and some others — prehistoric life has been found. Starting in the eighties, and especially in the nineties, the situation regarding knowledge of troglobitic fauna in the Balearic Islands underwent a 180-degree turn. The lead researcher of the project, Damià Jaume, has described over the last ten years up to 43 new species of crustaceans, including 15 new genera and two new families for this type of fauna, especially those inhabiting the aforementioned anchialine caves. Of these new species, 18 were found in caves surveyed in the Balearic Islands.\n\nThe Cova de Na Barxa is considered a Natural Site of special biological interest. J. A. Encinas S. Inventory listing of natural underground features of the Balearic Islands. 2006. JAES Editions.",
  "has_photos": true,
  "images": [
    "http://www.mallorcaverde.es/imagenes/espeleo/cova-de-na-barxa/cova-de-na-barxa-1.jpg",
    "http://www.mallorcaverde.es/imagenes/espeleo/cova-de-na-barxa/cova-de-na-barxa-6.jpg",
    "http://www.mallorcaverde.es/imagenes/espeleo/cova-de-na-barxa/cova-de-na-barxa-7.jpg"
  ],
  "lat": 39.685687,
  "lng": 3.458496,
  "topo_map": "http://www.mallorcaverde.es/imagenes/mapa-topografico-espeleo/COVA%20DE%20NA%20BARXA.jpg"
}